<?xml version="1.0" encoding="UTF-8"?>
<song>
<sections_number>6</sections_number>
<verse_number>3</verse_number>
<chorus_number>3</chorus_number>
<chorus_length>271</chorus_length>
<verse number="1">Eins, zwei, drei, vier, funf,
sechs, sieben, acht, neun, aus
Alle warten auf das Licht
Furchtet euch, furchtet euch nicht
Die Sonne scheint mir aus den Augen
Sie wird heut nacht nicht untergehen
Und die Welt zahlt laut bis zehn
</verse>
<chorus number="1">Eins... hier kommt die Sonne
Zwei... hier kommt die Sonne
Drei... sie ist der hellste Stern von allen
Vier... hier kommt die Sonne
</chorus>
<verse number="2">Die Sonne scheint mir aus den handen
Kann verbrennen kann euch blenden
Wenn sie aus den Fausten bricht
Legt sich Eis auf das Gesicht
Sie wird heut Nacht nicht untergehen
und die Welt zahlt laut bis zehn
</verse>
<chorus number="2">Eins... hier kommt die Sonne
Zwei... hier kommt die Sonne
Drei... sie ist der hellste Stern von allen
Vier... hier kommt die Sonne
Funf... hier kommt die Sonne
Sechs... hier kommt die Sonne
Sieben... sie ist der hellste Stern von allen
Acht , neun... hier kommt die Sonne
</chorus>
<verse number="3">Die Sonne scheint mir aus den Handen
Kann verbrennen, kann dich blenden
Wenn sie aus den Fausten bricht
Legt sich heiss auf dein Gesicht
Legt sich schmerzend auf die Brust
Das Gleichgewicht wird zum Verlust
l asst dich hart zu Boden gehen
Und die Welt zahlt laut bis zehn
</verse>
<chorus number="3">Eins... hier kommt die Sonne
Zwei... hier kommt die Sonne
Drei... sie ist der hellste Stern von allen
Vier... hier kommt die Sonne
Funf... hier kommt die Sonne
Sechs... hier kommt die Sonne
Sieben... sie ist der hellste Stern von allen
Acht , neun... hier kommt die Sonne
</chorus>
</song>
