<?xml version="1.0" encoding="UTF-8"?>
<song>
<sections_number>7</sections_number>
<verse_number>4</verse_number>
<chorus_number>3</chorus_number>
<chorus_length>158</chorus_length>
<verse number="1">Она любит пугливую речь,
Апликацию леса в реке вертикальны,
Ее почерк машинный, наскальный,
Ее брови, как сон тишины.
</verse>
<verse number="2">Она любит варенье из ласк,
Арифметику лета и опыты крови.
И ее изумрудные брови
Колосятся под знаком луны.
</verse>
<chorus number="1">Ты узнаешь ее из тысячи.
Ее образ на сердце высечен.
Ты узнаешь ее из тысячи
По словам, по глазам, по голосу,
Ее образ на сердце высечен
Ароматами гладиолуса.
</chorus>
<verse number="3">Она любит речные часы
Позывные дождя в полутемной беседке,
Осень тянется в запертой клетке
Долго, долго до самой весны.
</verse>
<chorus number="2">Ты узнаешь ее из тысячи.
Ее образ на сердце высечен.
Ты узнаешь ее из тысячи
По словам, по глазам, по голосу,
Ее образ на сердце высечен
Ароматами гладиолуса.
</chorus>
<verse number="4">Ты ее узнаешь, она будет твоей,
Вот только нужно тебе поверить
Хоть чуть-чуть в свою удачу,
Тот, кто ищет и верит, получает свое,
Не бывает иначе, ты узнаешь ее.
</verse>
<chorus number="3">Ты узнаешь ее из тысячи
По словам, по глазам, по голосу,
Ее образ на сердце высечен
Ароматами гладиолуса.
</chorus>
</song>
